LICENSE
MANIFEST.in
README.rst
setup.py
communico/__init__.py
communico/admin.py
communico/apps.py
communico/forms.py
communico/models.py
communico/tests.py
communico/urls.py
communico/views.py
communico.egg-info/PKG-INFO
communico.egg-info/SOURCES.txt
communico.egg-info/dependency_links.txt
communico.egg-info/top_level.txt
communico/templates/communico/base.html
communico/templates/communico/contact_form.html